set2/q8/fa.vhd
-- fa.vhd: Module to implement a basic full adder module
library ieee;
use ieee.std_logic_1164.all;

entity fa is
	port(A, B, Cin : in std_logic; S, Cout : out std_logic);
end fa;

architecture dataflow of fa is

	-- introduce propagation delay to see the effects of cascading
	-- in a ripple carry adder that will be constructed out of this.
	constant prop_delay : time := 10 ns;

begin

	S	 <= (A xor B xor Cin)					after prop_delay;
	Cout <= ((Cin and (A xor B)) or (A and B))  after prop_delay;

end architecture;

set2/q8/worst_delay.vhd
-- worst_delay.vhd: Module to find the worst delay for a ripple carry adders

library ieee;
use ieee.std_logic_1164.all;

-- create a generic N bit adder
entity rca is
	generic(nbits : integer);
	port(
			-- inputs
			A	 : in std_logic_vector(nbits-1 downto 0);
			B	 : in std_logic_vector(nbits-1 downto 0);

			-- outputs
			S	 : out std_logic_vector(nbits-1 downto 0);
			Cout : out std_logic
		);
end rca;

architecture structural of rca is

	signal carry : std_logic_vector(nbits-1 downto 0);

begin

	rca_nbit : for i in 0 to (nbits-1) generate

		fa0 : if i = 0 generate
			bit0 : entity work.fa(dataflow)
				   port map(A	 => A(i),
							B	 => B(i),
					    	S	 => S(i),
							Cin	 => '0',
							Cout => carry(i));
		end generate fa0;

		fax : if i /= 0 generate
			bitx : entity work.fa(dataflow)
				   port map(A	 => A(i),
							B	 => B(i),
					    	S	 => S(i),
							Cin	 => carry(i-1),
							Cout => carry(i));
		end generate fax;

	end generate rca_nbit;

	Cout <= carry(nbits-1);

end structural;

set2/q8/worst_delay_tb.vhd
-- worst_delay_tb.vhd: Testbench to test the ripple carry adder to find worst case delay
-- todo: finish this, ask sayan sir how to proceed

library ieee;
use ieee.std_logic_1164.all;

entity worst_delay_tb is
end worst_delay_tb;

architecture sim of worst_delay_tb is

	-- define the number of bits to instantiate the RCA with
	constant nbits : integer := 4;

	-- signals to test the device with
	signal   A	   : std_logic_vector(nbits-1 downto 0);
	signal	 B	   : std_logic_vector(nbits-1 downto 0);
	signal	 S	   : std_logic_vector(nbits-1 downto 0);
	signal   Cout  : std_logic;

	-- variables to keep track of time elapsed
	signal elapsed : time;

begin

	-- instantiate an RCA module
	rca_nbit : entity work.rca(structural)
			   generic map(nbits => nbits)
			   port map(A    => A,
						B    => B,
						S	 => S,
						Cout => Cout);

	-- apply stimulus
	find_worst_case: process is 
	begin
		A <= x"A"; B <= x"1"; wait for 100 ns;
		A <= x"B"; B <= x"2"; wait for 100 ns;
		A <= x"C"; B <= x"3"; wait for 100 ns;
		A <= x"D"; B <= x"4"; wait for 100 ns;
		wait;
	end process;
	
end sim;

set2/q8/worst_delay.vcd
$date
  Sat Oct 29 14:38:43 2022
$end
$version
  GHDL v0
$end
$timescale
  1 fs
$end
$scope module standard $end
$upscope $end
$scope module std_logic_1164 $end
$upscope $end
$scope module worst_delay_tb $end
$var reg 4 ! a[3:0] $end
$var reg 4 " b[3:0] $end
$var reg 4 # s[3:0] $end
$var reg 1 $ cout $end
$comment elapsed is not handled $end
$scope module rca_nbit $end
$var reg 4 % a[3:0] $end
$var reg 4 & b[3:0] $end
$var reg 4 ' s[3:0] $end
$var reg 1 ( cout $end
$var reg 4 ) carry[3:0] $end
$scope module rca_nbit(0) $end
$scope module fa0 $end
$scope module bit0 $end
$var reg 1 * a $end
$var reg 1 + b $end
$var reg 1 , cin $end
$var reg 1 - s $end
$var reg 1 . cout $end
$upscope $end
$upscope $end
$upscope $end
$scope module rca_nbit(1) $end
$scope module fax $end
$scope module bitx $end
$var reg 1 / a $end
$var reg 1 0 b $end
$var reg 1 1 cin $end
$var reg 1 2 s $end
$var reg 1 3 cout $end
$upscope $end
$upscope $end
$upscope $end
$scope module rca_nbit(2) $end
$scope module fax $end
$scope module bitx $end
$var reg 1 4 a $end
$var reg 1 5 b $end
$var reg 1 6 cin $end
$var reg 1 7 s $end
$var reg 1 8 cout $end
$upscope $end
$upscope $end
$upscope $end
$scope module rca_nbit(3) $end
$scope module fax $end
$scope module bitx $end
$var reg 1 9 a $end
$var reg 1 : b $end
$var reg 1 ; cin $end
$var reg 1 < s $end
$var reg 1 = cout $end
$upscope $end
$upscope $end
$upscope $end
$upscope $end
$upscope $end
$enddefinitions $end
#0
b1010 !
b0001 "
bUUUU #
U$
b1010 %
b0001 &
bUUUU '
U(
bUUUU )
0*
1+
0,
U-
U.
1/
00
U1
U2
U3
04
05
U6
U7
U8
19
0:
U;
U<
U=
#10000000
bUUU1 #
bUUU1 '
bU0U0 )
1-
0.
01
U2
U3
U7
08
0;
U<
U=
#20000000
b1U11 #
0$
b1U11 '
0(
b0000 )
12
03
06
1<
0=
#30000000
b1011 #
b1011 '
07
08
#100000000
b1011 !
b0010 "
b1011 %
b0010 &
1*
0+
10
#110000000
b1001 #
b1001 '
b0010 )
1-
0.
02
13
16
#120000000
b1101 #
b1101 '
17
08
#200000000
b1100 !
b0011 "
b1100 %
b0011 &
0*
1+
0/
14
#210000000
b1011 #
b1011 '
b0100 )
1-
0.
12
03
06
07
18
1;
#220000000
b0111 #
1$
b0111 '
1(
b1000 )
17
08
0;
0<
1=
#230000000
b1111 #
0$
b1111 '
0(
b0000 )
1<
0=
#300000000
b1101 !
b0100 "
b1101 %
b0100 &
1*
0+
00
15
#310000000
b1001 #
b1001 '
b0100 )
1-
0.
02
03
07
18
1;
#320000000
b0001 #
1$
b0001 '
1(
b1100 )
0<
1=
