set1/q4/ram16x8.vhd
-- ram16x8.vhd: Module to implement a 16 word 8 bit RAM

library ieee;
use ieee.std_logic_1164.all;
use ieee.numeric_std.all;

entity ram16x8 is
	port(
			address		: in	std_logic_vector(3 downto 0); -- 16 words = 4 addr bits
			data_in		: in	std_logic_vector(7 downto 0); -- 8 bits / 1 word
			rdwr		: in	std_logic;					  -- 1 = read, 0 = write
			clock		: in	std_logic;
			data_out	: out	std_logic_vector(7 downto 0)  -- output bus
		);
end ram16x8;

architecture behavioral of ram16x8 is
	-- memory can be syntheized from arrays: define new type for creating RAM from array
	-- define a type for a 16x8 bit memory
	type memory is array (0 to 15) of std_logic_vector(7 downto 0);
	-- initial values of words in the ram
	signal ram : memory := (
		x"00", x"11", x"22", x"33", -- 0x00 to 0x03
		x"44", x"55", x"66", x"77", -- 0x04 to 0x07
		x"88", x"99", x"AA", x"BB", -- 0x08 to 0x0B
		x"CC", x"DD", x"EE", x"FF"  -- 0x0C to 0x0F
	);
	-- define function acting as 3 bit decoder
	function decode(addr3bit : in std_logic_vector(3 downto 0)) return integer is
	begin
		return to_integer(unsigned(addr3bit));
	end function;
begin
	process(clock) is
	begin
		if rising_edge(clock) then	-- at clock edge sample, the read/write signal
			if rdwr = '1' then		-- read operation
				data_out <= ram(decode(address));
			elsif rdwr = '0' then	-- write operation
				ram(decode(address)) <= data_in;
			end if;
		end if;
	end process;
end behavioral;

set1/q4/ram16x8_tb.vhd
-- ram16x8_tb.vhd: Testbench to test the 16 word 8 bit RAM

library ieee;
use ieee.std_logic_1164.all;

entity ram16x8_tb is
end ram16x8_tb;

architecture sim of ram16x8_tb is
	constant cycle  : time	:= 10 ns;
	signal address	: std_logic_vector(3 downto 0);
	signal data_in	: std_logic_vector(7 downto 0);
	signal rdwr		: std_logic;
	signal clock	: std_logic := '1';
	signal data_out	: std_logic_vector(7 downto 0);
begin
	clock <= not clock after cycle/2;
	uut : entity work.ram16x8(behavioral)
		  port map(
					address => address,
					data_in	=> data_in,
					rdwr	=> rdwr,
					clock	=> clock,
					data_out => data_out
				  );
	process begin
		wait for 0.3*cycle;
		-- read contents of the RAM
		rdwr	<= '1';
		address <= "0000"; wait for cycle;
		address <= "0010"; wait for cycle;
		address <= "0101"; wait for cycle;
		address <= "1010"; wait for cycle;

		-- write contents into the RAM
		rdwr	<= '0';
		address <= "0000"; data_in <= x"FF"; wait for cycle;
		address <= "0010"; data_in <= x"EE"; wait for cycle;
		address <= "0101"; data_in <= x"22"; wait for cycle;
		address <= "1010"; data_in <= x"55"; wait for cycle;

		-- read contents of the RAM
		rdwr <= '1';
		address <= "0000"; wait for cycle;
		address <= "0010"; wait for cycle;
		address <= "0101"; wait for cycle;
		address <= "1010"; wait for cycle;
		wait;
	end process;
end sim;

set1/q4/ram16x8.vcd
$date
  Wed Nov 16 23:57:07 2022
$end
$version
  GHDL v0
$end
$timescale
  1 fs
$end
$scope module standard $end
$upscope $end
$scope module std_logic_1164 $end
$upscope $end
$scope module numeric_std $end
$upscope $end
$scope module ram16x8_tb $end
$var reg 4 ! address[3:0] $end
$var reg 8 " data_in[7:0] $end
$var reg 1 # rdwr $end
$var reg 1 $ clock $end
$var reg 8 % data_out[7:0] $end
$scope module uut $end
$var reg 4 & address[3:0] $end
$var reg 8 ' data_in[7:0] $end
$var reg 1 ( rdwr $end
$var reg 1 ) clock $end
$var reg 8 * data_out[7:0] $end
$comment ram is not handled $end
$upscope $end
$upscope $end
$enddefinitions $end
#0
bUUUU !
bUUUUUUUU "
U#
1$
bUUUUUUUU %
bUUUU &
bUUUUUUUU '
U(
1)
bUUUUUUUU *
#3000000
b0000 !
1#
b0000 &
1(
#5000000
0$
0)
#10000000
1$
b00000000 %
1)
b00000000 *
#13000000
b0010 !
b0010 &
#15000000
0$
0)
#20000000
1$
b00100010 %
1)
b00100010 *
#23000000
b0101 !
b0101 &
#25000000
0$
0)
#30000000
1$
b01010101 %
1)
b01010101 *
#33000000
b1010 !
b1010 &
#35000000
0$
0)
#40000000
1$
b10101010 %
1)
b10101010 *
#43000000
b0000 !
b11111111 "
0#
b0000 &
b11111111 '
0(
#45000000
0$
0)
#50000000
1$
1)
#53000000
b0010 !
b11101110 "
b0010 &
b11101110 '
#55000000
0$
0)
#60000000
1$
1)
#63000000
b0101 !
b00100010 "
b0101 &
b00100010 '
#65000000
0$
0)
#70000000
1$
1)
#73000000
b1010 !
b01010101 "
b1010 &
b01010101 '
#75000000
0$
0)
#80000000
1$
1)
#83000000
b0000 !
1#
b0000 &
1(
#85000000
0$
0)
#90000000
1$
b11111111 %
1)
b11111111 *
#93000000
b0010 !
b0010 &
#95000000
0$
0)
#100000000
1$
b11101110 %
1)
b11101110 *
#103000000
b0101 !
b0101 &
#105000000
0$
0)
#110000000
1$
b00100010 %
1)
b00100010 *
#113000000
b1010 !
b1010 &
#115000000
0$
0)
#120000000
1$
b01010101 %
1)
b01010101 *
