set2/q3/bcd7seg.vhd
-- bcd7seg.vhd: Module to convert BCD into segments for an ACTIVE LOW 7 segment display
-- https://allaboutfpga.com/bcd-to-7-segment-decoder-vhdl-code/#BCD_to_7_segment_display_Decoder_Truth_Table

library ieee;
use ieee.std_logic_1164.all;

entity bcd7seg is
	port(
			X : in std_logic_vector(3 downto 0);
			Y : out std_logic_vector(6 downto 0)
		);
end bcd7seg;


architecture dataflow of bcd7seg is
begin

	Y(6) <= X(0) or X(2) or (X(1) and X(3)) or ((not X(1)) and (not X(3)));

	Y(5) <= (not X(1)) and ((not X(2)) and (not X(3))) and (X(2) and X(3));
	
	Y(4) <= X(1) or (not X(2)) or X(3);

	Y(3) <= ((not X(1)) and (not X(3))) or (X(2) and (not X(3))) or 
			(X(1) and (not X(2)) and X(3)) or ((not X(1)) and X(2)) or X(0);

	Y(2) <= ((not X(1)) and (not X(3))) or (X(2) and (not X(3)));

	Y(1) <= X(0) or ((not X(2)) and (not X(3))) or (X(1) and (not X(2))) or 
			(X(1) and (not X(3)));

	Y(0) <= X(0) or (X(1) and (not X(2))) or ((not X(1)) and X(2)) or 
			(X(2) and (not X(3)));

end dataflow;

architecture behavioral of bcd7seg is
begin
	process(X) is
	begin
		case X is
			when x"0" =>
				Y <= "0000001"; -- 0
			when x"1" =>
				Y <= "1001111"; -- 1
			when x"2" =>
				Y <= "0010010"; -- 2
			when x"3" =>
				Y <= "0000110"; -- 3
			when x"4" =>
				Y <= "1001100"; -- 4
			when x"5" =>
				Y <= "0100100"; -- 5
			when x"6" =>
				Y <= "0100000"; -- 6
			when x"7" =>
				Y <= "0001111"; -- 7
			when x"8" =>
				Y <= "0000000"; -- 8
			when x"9" =>
				Y <= "0000100"; -- 9
			when others =>
				Y <= (others => 'X');
		end case;
	end process;
end behavioral;

-- todo: correct dataflow model
-- todo: structural model
-- todo: behavioral model: check out this post -
--       https://stackoverflow.com/questions/34000296/case-statement-error-message-in-vhdl
-- todo: ask sayan sir about correction to question:
--	1. should it be structural model? or behavioral ?
--	2. will the seven segment device be active high or active low

set2/q3/bcd7seg_tb.vhd
-- bcd7seg_tb.vhd: Testbench to test the working of the BCD to 7 Segment Decoder

library ieee;
use ieee.std_logic_1164.all;

entity bcd7seg_tb is
end bcd7seg_tb;

architecture sim of bcd7seg_tb is

	-- declare a component for the module to be tested
	component bcd7seg is
		port(X : in std_logic_vector(3 downto 0);
			 Y : out std_logic_vector(6 downto 0));
	end component;

	-- stimulus signals
	signal tX : std_logic_vector(3 downto 0);
	signal tY1 : std_logic_vector(6 downto 0);
	signal tY2 : std_logic_vector(6 downto 0);

begin

	uut1 : entity work.bcd7seg(dataflow)
		   port map(X => tX, Y => tY1);

	uut2 : entity work.bcd7seg(behavioral)
		   port map(X => tX, Y => tY2);

	process is
	begin
		tX <= x"0"; wait for 10 ns;
		tX <= x"1"; wait for 10 ns;
		tX <= x"2"; wait for 10 ns;
		tX <= x"3"; wait for 10 ns;
		tX <= x"4"; wait for 10 ns;
		tX <= x"5"; wait for 10 ns;
		tX <= x"6"; wait for 10 ns;
		tX <= x"7"; wait for 10 ns;
		tX <= x"8"; wait for 10 ns;
		tX <= x"9"; wait for 10 ns;
		wait;
	end process;

end sim;

set2/q3/bcd7seg.vcd
$date
  Thu Oct 27 16:25:05 2022
$end
$version
  GHDL v0
$end
$timescale
  1 fs
$end
$scope module standard $end
$upscope $end
$scope module std_logic_1164 $end
$upscope $end
$scope module bcd7seg_tb $end
$var reg 4 ! tx[3:0] $end
$var reg 7 " ty1[6:0] $end
$var reg 7 # ty2[6:0] $end
$scope module uut1 $end
$var reg 4 $ x[3:0] $end
$var reg 7 % y[6:0] $end
$upscope $end
$scope module uut2 $end
$var reg 4 & x[3:0] $end
$var reg 7 ' y[6:0] $end
$upscope $end
$upscope $end
$enddefinitions $end
#0
b0000 !
b1011110 "
b0000001 #
b0000 $
b1011110 %
b0000 &
b0000001 '
#10000000
b0001 !
b1011111 "
b1001111 #
b0001 $
b1011111 %
b0001 &
b1001111 '
#20000000
b0010 !
b0010011 "
b0010010 #
b0010 $
b0010011 %
b0010 &
b0010010 '
#30000000
b0011 !
b1011011 "
b0000110 #
b0011 $
b1011011 %
b0011 &
b0000110 '
#40000000
b0100 !
b1001101 "
b1001100 #
b0100 $
b1001101 %
b0100 &
b1001100 '
#50000000
b0101 !
b1001111 "
b0100100 #
b0101 $
b1001111 %
b0101 &
b0100100 '
#60000000
b0110 !
b1011111 "
b0100000 #
b0110 $
b1011111 %
b0110 &
b0100000 '
#70000000
b0111 !
b0001111 #
b0111 $
b0111 &
b0001111 '
#80000000
b1000 !
b0010000 "
b0000000 #
b1000 $
b0010000 %
b1000 &
b0000000 '
#90000000
b1001 !
b1011011 "
b0000100 #
b1001 $
b1011011 %
b1001 &
b0000100 '
