set3/q3/crc_8_ccitt.vhd
-- crc.vhd: Module to implement a CRC generator using the CRC-8-CCITT scheme
-- for which the generator polynomial is G(x) = x^8 + x^7 + x^3 + x^2 + x^1 + 1

library ieee;
use ieee.std_logic_1164.all;

entity crc_8_ccitt is
	port(DIN  : in std_logic;
		 CLK  : in std_logic;
		 CRC  : out std_logic_vector(7 downto 0);
		 VOUT : out std_logic);
end crc_8_ccitt;

architecture rtl of crc_8_ccitt is
	signal D	  : std_logic_vector(7 downto 0) := (others => '0');
	signal Q	  : std_logic_vector(7 downto 0) := (others => '0');
	signal count  : integer := 0;
begin
	-- reset register or shift the data into flip flops at every clock edge
	shift : process(CLK) begin
		if rising_edge(CLK) and (count < 16) then
			for i in 0 to 7 loop
				Q(i) <= D(i);
			end loop;
			count <= count + 1;
		end if;
	end process shift;

	-- flip data bits conditionally at locations determined by the generator polynomial
	process(Q, DIN) begin
		for i in 0 to 7 loop
			case i is
				when 0 => D(0) <= DIN  xor Q(7);
				when 2 => D(2) <= Q(1) xor Q(7);
				when 3 => D(3) <= Q(2) xor Q(7);
				when 7 => D(7) <= Q(6) xor Q(7);
				when others => D(i) <= Q(i-1);
			end case;
		end loop;
	end process;

	-- make the Q register available as the bits of the output CRC
	CRC <= Q;

	-- indicate when the output is valid
	VOUT <= '1' when count = 16 else '0';

end rtl;

set3/q3/crc_8_ccitt_tb.vhd
-- crc_8_ccitt_tb.vhd: Testbench to test the CRC-8-CCITT module using sample inputs

library ieee;
use ieee.std_logic_1164.all;
use ieee.numeric_std.all;

entity crc_8_ccitt_tb is
end crc_8_ccitt_tb;

architecture sim of crc_8_ccitt_tb is
	constant cycle : time := 10 ns;
	signal   DIN   : std_logic;
	signal   CLK   : std_logic := '0';
	signal   CRC   : std_logic_vector(7 downto 0);
	signal   VOUT  : std_logic;
	signal   msg   : std_logic_vector(15 downto 0) := x"4800";
begin
	CLK <= not CLK after cycle/2;
	uut : entity work.crc_8_ccitt(rtl)
		  port map(DIN  => DIN,
			       CLK  => CLK,
			       CRC  => CRC,
			       VOUT => VOUT);
	process begin
		wait for 0.3*cycle;
		for i in msg'high downto 0 loop -- shift in bits into the module MSB first
			DIN <= msg(i);
			wait for cycle;
		end loop;
		wait;
	end process;
end sim;

set3/q3/crc_8_ccitt.vcd
$date
  Wed Nov 23 19:56:07 2022
$end
$version
  GHDL v0
$end
$timescale
  1 fs
$end
$scope module standard $end
$upscope $end
$scope module std_logic_1164 $end
$upscope $end
$scope module numeric_std $end
$upscope $end
$scope module crc_8_ccitt_tb $end
$var reg 1 ! din $end
$var reg 1 " clk $end
$var reg 8 # crc[7:0] $end
$var reg 1 $ vout $end
$var reg 16 % msg[15:0] $end
$scope module uut $end
$var reg 1 & din $end
$var reg 1 ' clk $end
$var reg 8 ( crc[7:0] $end
$var reg 1 ) vout $end
$var reg 8 * d[7:0] $end
$var reg 8 + q[7:0] $end
$var integer 32 , count $end
$upscope $end
$upscope $end
$enddefinitions $end
#0
U!
0"
b00000000 #
0$
b0100100000000000 %
U&
0'
b00000000 (
0)
b0000000U *
b00000000 +
b0 ,
#3000000
0!
0&
b00000000 *
#5000000
1"
1'
b1 ,
#10000000
0"
0'
#13000000
1!
1&
b00000001 *
#15000000
1"
b00000001 #
1'
b00000001 (
b00000011 *
b00000001 +
b10 ,
#20000000
0"
0'
#23000000
0!
0&
b00000010 *
#25000000
1"
b00000010 #
1'
b00000010 (
b00000100 *
b00000010 +
b11 ,
#30000000
0"
0'
#33000000
#35000000
1"
b00000100 #
1'
b00000100 (
b00001000 *
b00000100 +
b100 ,
#40000000
0"
0'
#43000000
1!
1&
b00001001 *
#45000000
1"
b00001001 #
1'
b00001001 (
b00010011 *
b00001001 +
b101 ,
#50000000
0"
0'
#53000000
0!
0&
b00010010 *
#55000000
1"
b00010010 #
1'
b00010010 (
b00100100 *
b00010010 +
b110 ,
#60000000
0"
0'
#63000000
#65000000
1"
b00100100 #
1'
b00100100 (
b01001000 *
b00100100 +
b111 ,
#70000000
0"
0'
#73000000
#75000000
1"
b01001000 #
1'
b01001000 (
b10010000 *
b01001000 +
b1000 ,
#80000000
0"
0'
#83000000
#85000000
1"
b10010000 #
1'
b10010000 (
b10101101 *
b10010000 +
b1001 ,
#90000000
0"
0'
#93000000
#95000000
1"
b10101101 #
1'
b10101101 (
b11010111 *
b10101101 +
b1010 ,
#100000000
0"
0'
#103000000
#105000000
1"
b11010111 #
1'
b11010111 (
b00100011 *
b11010111 +
b1011 ,
#110000000
0"
0'
#113000000
#115000000
1"
b00100011 #
1'
b00100011 (
b01000110 *
b00100011 +
b1100 ,
#120000000
0"
0'
#123000000
#125000000
1"
b01000110 #
1'
b01000110 (
b10001100 *
b01000110 +
b1101 ,
#130000000
0"
0'
#133000000
#135000000
1"
b10001100 #
1'
b10001100 (
b10010101 *
b10001100 +
b1110 ,
#140000000
0"
0'
#143000000
#145000000
1"
b10010101 #
1'
b10010101 (
b10100111 *
b10010101 +
b1111 ,
#150000000
0"
0'
#153000000
#155000000
1"
b10100111 #
1$
1'
b10100111 (
1)
b11000011 *
b10100111 +
b10000 ,
