set2/q10/counter_control.vhd
-- counter_control.vhd: 5 bit counter that prodcues high for 4th, 20th, and 24th cycles

library ieee;
use ieee.std_logic_1164.all;
use ieee.numeric_std.all;

entity counter_control is
	port(   -- inputs
			clock   : in std_logic;
			reset   : in std_logic;
			-- outputs
			control : out std_logic
		);
end counter_control;

architecture behavioral of counter_control is

	-- intermediate signal for counting clock edges
	signal state : unsigned(4 downto 0);

begin

	process(clock, reset) is
	begin
		-- asynchronous reset
		if reset = '1' then
			state <= 0;
		-- increment state whenever a clock edge is received
		elsif rising_edge(clock) then
			state <= state + 1;
		end if;
	end process;

	control <= '1' when state = 3 or state = 19 or state = 23 else '0';

end behavioral;

set2/q10/counter_control_tb.vhd
-- counter_control_tb.vhd: Testbench to test the counter_control

library ieee;
use ieee.std_logic_1164.all;
use ieee.numeric_std.all;

entity counter_control_tb is
end counter_control_tb;

architecture sim of counter_control_tb is

	constant freq	: integer	:= 100e6; 
	constant cycle	: time		:= 1000 ms / freq;

	signal clock	: std_logic := '1';
	signal reset	: std_logic;
	signal control	: std_logic := '0';

begin

	-- generate clock signal
	clock <= not clock after 10 ns;

	-- instantiate module to be tested
	uut : entity work.counter_control(behavioral)
	      port map(clock => clock, reset => reset, control => control);

	-- apply stimulus
	process is
	begin
		-- reset the device then bring it out of reset
		reset <= '1';
		wait for 0.3*cycle;
		reset <= '0'; 
		wait;
	end process;

end sim;

set2/q10/counter_control.vcd
$date
  Fri Oct 28 05:20:21 2022
$end
$version
  GHDL v0
$end
$timescale
  1 fs
$end
$scope module standard $end
$upscope $end
$scope module std_logic_1164 $end
$upscope $end
$scope module numeric_std $end
$upscope $end
$scope module counter_control_tb $end
$var reg 1 ! clock $end
$var reg 1 " reset $end
$var reg 1 # control $end
$scope module uut $end
$var reg 1 $ clock $end
$var reg 1 % reset $end
$var reg 1 & control $end
$var reg 5 ' state[4:0] $end
$upscope $end
$upscope $end
$enddefinitions $end
#0
1!
1"
0#
1$
1%
0&
b00000 '
#3000000
0"
0%
#10000000
0!
0$
#20000000
1!
1$
b00001 '
#30000000
0!
0$
#40000000
1!
1$
b00010 '
#50000000
0!
0$
#60000000
1!
1#
1$
1&
b00011 '
#70000000
0!
0$
#80000000
1!
0#
1$
0&
b00100 '
#90000000
0!
0$
#100000000
1!
1$
b00101 '
#110000000
0!
0$
#120000000
1!
1$
b00110 '
#130000000
0!
0$
#140000000
1!
1$
b00111 '
#150000000
0!
0$
#160000000
1!
1$
b01000 '
#170000000
0!
0$
#180000000
1!
1$
b01001 '
#190000000
0!
0$
#200000000
1!
1$
b01010 '
#210000000
0!
0$
#220000000
1!
1$
b01011 '
#230000000
0!
0$
#240000000
1!
1$
b01100 '
#250000000
0!
0$
#260000000
1!
1$
b01101 '
#270000000
0!
0$
#280000000
1!
1$
b01110 '
#290000000
0!
0$
#300000000
1!
1$
b01111 '
#310000000
0!
0$
#320000000
1!
1$
b10000 '
#330000000
0!
0$
#340000000
1!
1$
b10001 '
#350000000
0!
0$
#360000000
1!
1$
b10010 '
#370000000
0!
0$
#380000000
1!
1#
1$
1&
b10011 '
#390000000
0!
0$
#400000000
1!
0#
1$
0&
b10100 '
#410000000
0!
0$
#420000000
1!
1$
b10101 '
#430000000
0!
0$
#440000000
1!
1$
b10110 '
#450000000
0!
0$
#460000000
1!
1#
1$
1&
b10111 '
#470000000
0!
0$
#480000000
1!
0#
1$
0&
b11000 '
#490000000
0!
0$
#500000000
1!
1$
b11001 '
#510000000
0!
0$
#520000000
1!
1$
b11010 '
#530000000
0!
0$
#540000000
1!
1$
b11011 '
#550000000
0!
0$
#560000000
1!
1$
b11100 '
#570000000
0!
0$
#580000000
1!
1$
b11101 '
#590000000
0!
0$
#600000000
1!
1$
b11110 '
#610000000
0!
0$
#620000000
1!
1$
b11111 '
#630000000
0!
0$
#640000000
1!
1$
b00000 '
#650000000
0!
0$
#660000000
1!
1$
b00001 '
#670000000
0!
0$
#680000000
1!
1$
b00010 '
#690000000
0!
0$
#700000000
1!
1#
1$
1&
b00011 '
#710000000
0!
0$
#720000000
1!
0#
1$
0&
b00100 '
#730000000
0!
0$
#740000000
1!
1$
b00101 '
#750000000
0!
0$
#760000000
1!
1$
b00110 '
#770000000
0!
0$
#780000000
1!
1$
b00111 '
#790000000
0!
0$
#800000000
1!
1$
b01000 '
#810000000
0!
0$
#820000000
1!
1$
b01001 '
#830000000
0!
0$
#840000000
1!
1$
b01010 '
#850000000
0!
0$
#860000000
1!
1$
b01011 '
#870000000
0!
0$
#880000000
1!
1$
b01100 '
#890000000
0!
0$
#900000000
1!
1$
b01101 '
#910000000
0!
0$
#920000000
1!
1$
b01110 '
#930000000
0!
0$
#940000000
1!
1$
b01111 '
#950000000
0!
0$
#960000000
1!
1$
b10000 '
#970000000
0!
0$
#980000000
1!
1$
b10001 '
#990000000
0!
0$
#1000000000
1!
1$
b10010 '
