set1/q1.a/n_input_gate.vhd
-- n_input_gate.vhd: Module to implement 6 basic logic gates with N bit inputs

library ieee;
use ieee.std_logic_1164.all;

entity n_input_gate is
	generic(N   : integer); -- make number of bits a generic
	port(input  : in  std_logic_vector(N-1 downto 0);
		 output : out std_logic);
end n_input_gate;

-- 1. N input AND Gate
architecture and_gate of n_input_gate is

	-- internal signal for holding intermediate stages of propagation
	signal data : std_logic_vector(N-2 downto 0);

begin

	-- loop through the input and perform repeated AND operation
	GATE : for i in 0 to N-2 generate
		
		BIT0: if (i = 0) generate
			data(i) <= input(i) and input(i+1);
		end generate BIT0;

		BITX: if (i /= 0) generate
			data(i) <= data(i-1) and input(i+1);
		end generate BITX;

	end generate GATE;

	-- data propagates to the output
	output <= data(N-2);

end and_gate;

-- 2. N input OR Gate
architecture or_gate of n_input_gate is
	signal data : std_logic_vector(N-2 downto 0);
begin
	GATE : for i in 0 to N-2 generate
		BIT0: if (i = 0) generate
			data(i) <= input(i) or input(i+1);
		end generate BIT0;
		BITX: if (i /= 0) generate
			data(i) <= data(i-1) or input(i+1);
		end generate BITX;
	end generate GATE;
	output <= data(N-2);
end or_gate;

-- 3. N input NAND Gate
architecture nand_gate of n_input_gate is
	signal data : std_logic_vector(N-2 downto 0);
begin
	GATE : for i in 0 to N-2 generate
		BIT0: if (i = 0) generate
			data(i) <= (not input(i)) or (not input(i+1));
		end generate BIT0;
		BITX: if (i /= 0) generate
			data(i) <= data(i-1) or (not input(i+1));
		end generate BITX;
	end generate GATE;
	output <= data(N-2);
end nand_gate;

-- 4. N input NOR Gate
architecture nor_gate of n_input_gate is
	signal data : std_logic_vector(N-2 downto 0);
begin
	GATE : for i in 0 to N-2 generate
		BIT0: if (i = 0) generate
			data(i) <= (not input(i)) and (not input(i+1));
		end generate BIT0;
		BITX: if (i /= 0) generate
			data(i) <= data(i-1) and (not input(i+1));
		end generate BITX;
	end generate GATE;
	output <= data(N-2);
end nor_gate;

-- 5. N input XOR Gate
architecture xor_gate of n_input_gate is
	signal data : std_logic_vector(N-2 downto 0);
begin
	GATE : for i in 0 to N-2 generate
		BIT0: if (i = 0) generate
			data(i) <= input(i) xor input(i+1);
		end generate BIT0;
		BITX: if (i /= 0) generate
			data(i) <= data(i-1) xor input(i+1);
		end generate BITX;
	end generate GATE;
	output <= data(N-2);
end xor_gate;

-- 6. N input XNOR Gate
architecture xnor_gate of n_input_gate is
	signal data : std_logic_vector(N-2 downto 0);
begin
	GATE : for i in 0 to N-2 generate
		BIT0: if (i = 0) generate
			data(i) <= input(i) xnor input(i+1);
		end generate BIT0;
		BITX: if (i /= 0) generate
			data(i) <= data(i-1) xnor input(i+1);
		end generate BITX;
	end generate GATE;
	output <= data(N-2);
end xnor_gate;

set1/q1.a/n_input_gate_tb.vhd
-- n_input_gate_tb.vhd : Testbench to test the modules for 6 distinct N-input gates

library ieee;
use ieee.std_logic_1164.all;

entity n_input_gate_tb is
end n_input_gate_tb;

architecture sim of n_input_gate_tb is

	-- define the number of bits
	constant nbits		 : integer := 8;

	-- declare common test signals for all the gates
	signal	 input		 : std_logic_vector(nbits-1 downto 0);
	signal	 output_AND  : std_logic;
	signal	 output_OR   : std_logic;
	signal	 output_NAND : std_logic;
	signal	 output_NOR  : std_logic;
	signal	 output_XOR  : std_logic;
	signal	 output_XNOR : std_logic;

begin
	-- instantiate different types of N input gates using their architecture
	and_n  : entity work.n_input_gate(and_gate)
			 generic map(N => nbits)
			 port map(input => input, output => output_AND);

	or_n   : entity work.n_input_gate(or_gate)
			 generic map(N => nbits)
			 port map(input => input, output => output_OR);

	nand_n  : entity work.n_input_gate(nand_gate)
			 generic map(N => nbits)
			 port map(input => input, output => output_NAND);

	nor_n : entity work.n_input_gate(nor_gate)
			 generic map(N => nbits)
			 port map(input => input, output => output_NOR);

	xor_n : entity work.n_input_gate(xor_gate)
			 generic map(N => nbits)
			 port map(input => input, output => output_XOR);

	xnor_n : entity work.n_input_gate(xnor_gate)
			 generic map(N => nbits)
			 port map(input => input, output => output_XNOR);

	-- apply common inputs to all the gates and observe their outputs
	stimulus: process is
	begin
		-- try to cover as many important test cases in as few inputs as possible
		input <= x"00"; wait for 10 ns;  -- all zeros
		input <= x"FF"; wait for 10 ns;	 -- all ones
		input <= x"01"; wait for 10 ns;  -- all except 1 zeros
		input <= x"80"; wait for 10 ns;  -- all except 1 zeros nibbles reversed
		input <= x"7F"; wait for 10 ns;	 -- all except 1 ones
		input <= x"F7"; wait for 10 ns;	 -- all except 1 ones nibbles reversed
		input <= x"AA"; wait for 10 ns;  -- even number of ones
		input <= x"E0"; wait for 10 ns;  -- odd number of ones 
		wait;
	end process;
end sim;

set1/q1.a/n_input_gate.vcd
$date
  Wed Nov  2 01:05:58 2022
$end
$version
  GHDL v0
$end
$timescale
  1 fs
$end
$scope module standard $end
$upscope $end
$scope module std_logic_1164 $end
$upscope $end
$scope module n_input_gate_tb $end
$var reg 8 ! input[7:0] $end
$var reg 1 " output_and $end
$var reg 1 # output_or $end
$var reg 1 $ output_nand $end
$var reg 1 % output_nor $end
$var reg 1 & output_xor $end
$var reg 1 ' output_xnor $end
$scope module and_n $end
$var reg 8 ( input[7:0] $end
$var reg 1 ) output $end
$var reg 7 * data[6:0] $end
$scope module gate(0) $end
$scope module bit0 $end
$upscope $end
$upscope $end
$scope module gate(1) $end
$scope module bitx $end
$upscope $end
$upscope $end
$scope module gate(2) $end
$scope module bitx $end
$upscope $end
$upscope $end
$scope module gate(3) $end
$scope module bitx $end
$upscope $end
$upscope $end
$scope module gate(4) $end
$scope module bitx $end
$upscope $end
$upscope $end
$scope module gate(5) $end
$scope module bitx $end
$upscope $end
$upscope $end
$scope module gate(6) $end
$scope module bitx $end
$upscope $end
$upscope $end
$upscope $end
$scope module or_n $end
$var reg 8 + input[7:0] $end
$var reg 1 , output $end
$var reg 7 - data[6:0] $end
$scope module gate(0) $end
$scope module bit0 $end
$upscope $end
$upscope $end
$scope module gate(1) $end
$scope module bitx $end
$upscope $end
$upscope $end
$scope module gate(2) $end
$scope module bitx $end
$upscope $end
$upscope $end
$scope module gate(3) $end
$scope module bitx $end
$upscope $end
$upscope $end
$scope module gate(4) $end
$scope module bitx $end
$upscope $end
$upscope $end
$scope module gate(5) $end
$scope module bitx $end
$upscope $end
$upscope $end
$scope module gate(6) $end
$scope module bitx $end
$upscope $end
$upscope $end
$upscope $end
$scope module nand_n $end
$var reg 8 . input[7:0] $end
$var reg 1 / output $end
$var reg 7 0 data[6:0] $end
$scope module gate(0) $end
$scope module bit0 $end
$upscope $end
$upscope $end
$scope module gate(1) $end
$scope module bitx $end
$upscope $end
$upscope $end
$scope module gate(2) $end
$scope module bitx $end
$upscope $end
$upscope $end
$scope module gate(3) $end
$scope module bitx $end
$upscope $end
$upscope $end
$scope module gate(4) $end
$scope module bitx $end
$upscope $end
$upscope $end
$scope module gate(5) $end
$scope module bitx $end
$upscope $end
$upscope $end
$scope module gate(6) $end
$scope module bitx $end
$upscope $end
$upscope $end
$upscope $end
$scope module nor_n $end
$var reg 8 1 input[7:0] $end
$var reg 1 2 output $end
$var reg 7 3 data[6:0] $end
$scope module gate(0) $end
$scope module bit0 $end
$upscope $end
$upscope $end
$scope module gate(1) $end
$scope module bitx $end
$upscope $end
$upscope $end
$scope module gate(2) $end
$scope module bitx $end
$upscope $end
$upscope $end
$scope module gate(3) $end
$scope module bitx $end
$upscope $end
$upscope $end
$scope module gate(4) $end
$scope module bitx $end
$upscope $end
$upscope $end
$scope module gate(5) $end
$scope module bitx $end
$upscope $end
$upscope $end
$scope module gate(6) $end
$scope module bitx $end
$upscope $end
$upscope $end
$upscope $end
$scope module xor_n $end
$var reg 8 4 input[7:0] $end
$var reg 1 5 output $end
$var reg 7 6 data[6:0] $end
$scope module gate(0) $end
$scope module bit0 $end
$upscope $end
$upscope $end
$scope module gate(1) $end
$scope module bitx $end
$upscope $end
$upscope $end
$scope module gate(2) $end
$scope module bitx $end
$upscope $end
$upscope $end
$scope module gate(3) $end
$scope module bitx $end
$upscope $end
$upscope $end
$scope module gate(4) $end
$scope module bitx $end
$upscope $end
$upscope $end
$scope module gate(5) $end
$scope module bitx $end
$upscope $end
$upscope $end
$scope module gate(6) $end
$scope module bitx $end
$upscope $end
$upscope $end
$upscope $end
$scope module xnor_n $end
$var reg 8 7 input[7:0] $end
$var reg 1 8 output $end
$var reg 7 9 data[6:0] $end
$scope module gate(0) $end
$scope module bit0 $end
$upscope $end
$upscope $end
$scope module gate(1) $end
$scope module bitx $end
$upscope $end
$upscope $end
$scope module gate(2) $end
$scope module bitx $end
$upscope $end
$upscope $end
$scope module gate(3) $end
$scope module bitx $end
$upscope $end
$upscope $end
$scope module gate(4) $end
$scope module bitx $end
$upscope $end
$upscope $end
$scope module gate(5) $end
$scope module bitx $end
$upscope $end
$upscope $end
$scope module gate(6) $end
$scope module bitx $end
$upscope $end
$upscope $end
$upscope $end
$upscope $end
$enddefinitions $end
#0
b00000000 !
0"
0#
1$
1%
0&
1'
b00000000 (
0)
b0000000 *
b00000000 +
0,
b0000000 -
b00000000 .
1/
b1111111 0
b00000000 1
12
b1111111 3
b00000000 4
05
b0000000 6
b00000000 7
18
b1010101 9
#10000000
b11111111 !
1"
1#
0$
0%
0&
1'
b11111111 (
1)
b1111111 *
b11111111 +
1,
b1111111 -
b11111111 .
0/
b0000000 0
b11111111 1
02
b0000000 3
b11111111 4
05
b0101010 6
b11111111 7
18
b1111111 9
#20000000
b00000001 !
0"
1$
1&
0'
b00000001 (
0)
b0000000 *
b00000001 +
b00000001 .
1/
b1111111 0
b00000001 1
b00000001 4
15
b1111111 6
b00000001 7
08
b0101010 9
#30000000
b10000000 !
1&
0'
b10000000 (
b10000000 +
b1000000 -
b10000000 .
b10000000 1
b0111111 3
b10000000 4
15
b1000000 6
b10000000 7
08
b0010101 9
#40000000
b01111111 !
1#
0%
1&
0'
b01111111 (
b0111111 *
b01111111 +
1,
b1111111 -
b01111111 .
b1000000 0
b01111111 1
02
b0000000 3
b01111111 4
15
b1101010 6
b01111111 7
08
b0111111 9
#50000000
b11110111 !
0"
1$
1&
0'
b11110111 (
0)
b0000011 *
b11110111 +
b11110111 .
1/
b1111100 0
b11110111 1
b11110111 4
15
b1010110 6
b11110111 7
08
b0000011 9
#60000000
b10101010 !
0&
1'
b10101010 (
b0000000 *
b10101010 +
b10101010 .
b1111111 0
b10101010 1
b10101010 4
05
b0110011 6
b10101010 7
18
b1100110 9
#70000000
b11100000 !
1&
0'
b11100000 (
b11100000 +
b1110000 -
b11100000 .
b11100000 1
b0001111 3
b11100000 4
15
b1010000 6
b11100000 7
08
b0000101 9
