set1/q3.d/ringcounter.vhd
-- ringcounter.vhd: Module to implement a 3 bit ring counter

library ieee;
use ieee.std_logic_1164.all;

entity ringcounter is
	generic(N : natural := 3);
	port(CLK  : in  std_logic; 
		 ORI  : in  std_logic;	-- synchronous active low overriding input
		 Y    : out std_logic_vector(N-1 downto 0));
end ringcounter;

architecture behavioral of ringcounter is
	signal data : std_logic_vector(N-1 downto 0);
begin
	process(CLK, ORI) is
	begin
		if rising_edge(CLK) then
			if ORI = '0' then
				data <= (0 => '1', others => '0'); -- set output to "001"
			else
				data(0) <= data(N-1);
				for i in 0 to N-2 loop
					data(i+1) <= data(i);
				end loop;
			end if;
		end if;
	end process;
	Y <= data;
end behavioral;

set1/q3.d/ringcounter_tb.vhd
-- ringcounter_tb.vhd: Testbench for testing ring counter

library ieee;
use ieee.std_logic_1164.all;

entity ringcounter_tb is
end ringcounter_tb;

architecture sim of ringcounter_tb is
	constant cycle : time := 10 ns;
	signal CLK : std_logic := '0';
	signal ORI : std_logic;
	signal Y   : std_logic_vector(2 downto 0);
begin
	CLK <= not CLK after cycle/2;
	uut : entity work.ringcounter(behavioral) 
	      port map(CLK => CLK, ORI => ORI, Y => Y);
	process begin
		ORI <= '0'; wait for 1.3*cycle;
		ORI <= '1'; wait for 6*cycle;
		wait;
	end process;
end sim;

set1/q3.d/ringcounter.vcd
$date
  Tue Nov 15 23:59:48 2022
$end
$version
  GHDL v0
$end
$timescale
  1 fs
$end
$scope module standard $end
$upscope $end
$scope module std_logic_1164 $end
$upscope $end
$scope module ringcounter_tb $end
$var reg 1 ! clk $end
$var reg 1 " ori $end
$var reg 3 # y[2:0] $end
$scope module uut $end
$var reg 1 $ clk $end
$var reg 1 % ori $end
$var reg 3 & y[2:0] $end
$var reg 3 ' data[2:0] $end
$upscope $end
$upscope $end
$enddefinitions $end
#0
0!
0"
bUUU #
0$
0%
bUUU &
bUUU '
#5000000
1!
b001 #
1$
b001 &
b001 '
#10000000
0!
0$
#13000000
1"
1%
#15000000
1!
b010 #
1$
b010 &
b010 '
#20000000
0!
0$
#25000000
1!
b100 #
1$
b100 &
b100 '
#30000000
0!
0$
#35000000
1!
b001 #
1$
b001 &
b001 '
#40000000
0!
0$
#45000000
1!
b010 #
1$
b010 &
b010 '
#50000000
0!
0$
#55000000
1!
b100 #
1$
b100 &
b100 '
#60000000
0!
0$
#65000000
1!
b001 #
1$
b001 &
b001 '
#70000000
0!
0$
#73000000
#75000000
1!
b010 #
1$
b010 &
b010 '
