set3/q6/one_counter.vhd
-- one_counter.vhd: Module to count the number of ones in a 16 bit binary number

library ieee;
use ieee.std_logic_1164.all;
use ieee.numeric_std.all;

entity one_counter is
	generic(nbits : integer);
	port(	
			-- inputs
			reset : in std_logic;
			clock : in std_logic;
			input : in std_logic; -- binary number as bit stream

			-- outputs: 16 bit binary number: maximum 16 1's so need 4 bits to hold count
			--			this number will be specified via generic at instantiation
			count : inout unsigned(nbits-1 downto 0)
		);
end one_counter;

architecture behavioral of one_counter is
begin
	process(clock, reset) is 
	begin
		if reset = '1' then
			count <= (others => '0');
		elsif rising_edge(clock) then
			if input = '1' then
				count <= count + 1;
			end if;
		end if;
	end process;
end behavioral;

set3/q6/one_counter_tb.vhd
-- one_counter_tb.vhd: Testbench to test the design of the 1's counter
-- todo: finish this

library ieee;
use ieee.std_logic_1164.all;
use ieee.numeric_std.all;

entity one_counter_tb is
end one_counter_tb;

architecture sim of one_counter_tb is

	constant freq   : integer   := 100e6;			-- 100 MHz clock
	constant period : time	    := 1000 ms / freq;	-- 10 ns cycle

	signal	 reset  : std_logic;
	signal	 input  : std_logic;
	signal   clock	: std_logic := '1';
	signal   count  : unsigned(3 downto 0);
	signal   stream : unsigned(15 downto 0) := x"A38E"; -- test bit stream

	-- A38E (hex) = 1010 0011 1000 1110 (binary) has 8 ones, so we expect 8 as
	-- as the answer

begin

	-- generate the clock signal 
	clock <= not clock after period/2;

	-- instantiate the counter module to test
	uut : entity work.one_counter(behavioral)
		  generic map(nbits => 4) -- need 4 bits for 16 bit number
		  port map(
					clock => clock,
					reset => reset,
					input => input,
					count => count
				  );

	-- simulation needs to be run for at least 16*periods
	stimulus: process is
	begin
		-- reset the device for little more than the first clock cycle
		reset <= '1'; wait for 1.3*period;

		-- then bring the device out of reset and inject input bit stream LSB first
		reset <= '0';
		for i in 0 to 15 loop
			input <= '0';
			wait for 0.4*period;
			input <= stream(i);
			wait for 0.6*period;
		end loop;

		-- assert reset once bit stream has been injected completely
		reset <= '1'; wait;
	end process stimulus;
	
end sim;

set3/q6/one_counter.vcd
$date
  Sat Oct 29 23:11:35 2022
$end
$version
  GHDL v0
$end
$timescale
  1 fs
$end
$scope module standard $end
$upscope $end
$scope module std_logic_1164 $end
$upscope $end
$scope module numeric_std $end
$upscope $end
$scope module one_counter_tb $end
$var reg 1 ! reset $end
$var reg 1 " input $end
$var reg 1 # clock $end
$var reg 4 $ count[3:0] $end
$var reg 16 % stream[15:0] $end
$scope module uut $end
$var reg 1 & reset $end
$var reg 1 ' clock $end
$var reg 1 ( input $end
$var reg 4 ) count[3:0] $end
$upscope $end
$upscope $end
$enddefinitions $end
#0
1!
U"
1#
b0000 $
b1010001110001110 %
1&
1'
U(
b0000 )
#5000000
0#
0'
#10000000
1#
1'
#13000000
0!
0"
0&
0(
#15000000
0#
0'
#17000000
#20000000
1#
1'
#23000000
#25000000
0#
0'
#27000000
1"
1(
#30000000
1#
b0001 $
1'
b0001 )
#33000000
0"
0(
#35000000
0#
0'
#37000000
1"
1(
#40000000
1#
b0010 $
1'
b0010 )
#43000000
0"
0(
#45000000
0#
0'
#47000000
1"
1(
#50000000
1#
b0011 $
1'
b0011 )
#53000000
0"
0(
#55000000
0#
0'
#57000000
#60000000
1#
1'
#63000000
#65000000
0#
0'
#67000000
#70000000
1#
1'
#73000000
#75000000
0#
0'
#77000000
#80000000
1#
1'
#83000000
#85000000
0#
0'
#87000000
1"
1(
#90000000
1#
b0100 $
1'
b0100 )
#93000000
0"
0(
#95000000
0#
0'
#97000000
1"
1(
#100000000
1#
b0101 $
1'
b0101 )
#103000000
0"
0(
#105000000
0#
0'
#107000000
1"
1(
#110000000
1#
b0110 $
1'
b0110 )
#113000000
0"
0(
#115000000
0#
0'
#117000000
#120000000
1#
1'
#123000000
#125000000
0#
0'
#127000000
#130000000
1#
1'
#133000000
#135000000
0#
0'
#137000000
#140000000
1#
1'
#143000000
#145000000
0#
0'
#147000000
1"
1(
#150000000
1#
b0111 $
1'
b0111 )
#153000000
0"
0(
#155000000
0#
0'
#157000000
#160000000
1#
1'
#163000000
#165000000
0#
0'
#167000000
1"
1(
#170000000
1#
b1000 $
1'
b1000 )
#173000000
1!
b0000 $
1&
b0000 )
