set3/q5/sa.vhd
-- sa.vhd: Module to implement an N-bit serial adder

library ieee;
use ieee.std_logic_1164.all;
use ieee.numeric_std.all;

entity sa is
	generic(nbits : integer);
	port(	-- inputs
			Clk  : in  std_logic;
			nRst : in  std_logic;
			A	 : in  std_logic_vector(nbits-1 downto 0);
			B    : in  std_logic_vector(nbits-1 downto 0);

			-- outputs
			Sum  : out std_logic_vector(nbits-1 downto 0);
			Ov   : out std_logic
		);
end sa;

architecture behavioral of sa is

	-- hold intermediate carry states
	signal carry : std_logic;

begin
	
	-- decribe serial addition action
	process(Clk, nRst) is
		variable i : integer := 0;
	begin
		if nRst = '0' then
			-- reset outputs and bit tracker
			Sum   <= (others => '0');
			carry <= '0';
			i	  :=  0;

		elsif rising_edge(Clk) and (i < nbits) then
			if i = 0 then
				carry <= '0';
			end if;

			-- implement full adder logic
			Sum(i) <= (A(i) xor B(i) xor carry);
			carry  <= (carry and (A(i) xor B(i))) or (A(i) and B(i));

			-- update the bit tracker
			i := i + 1;

		end if;
	end process;

	-- set the overflow bit equal to the last carry out
	Ov <= carry;

end architecture;

set3/q5/sa_tb.vhd
-- sa_tb.vhd: Testbench to test the N-bit serial adder module

library ieee;
use ieee.std_logic_1164.all;

entity sa_tb is
end sa_tb;

architecture sim of sa_tb is

	constant nbits  : integer := 8;
	constant freq   : integer := 100e6;
	constant period : time	  := 1000 ms / freq;
	
	signal   clk    : std_logic := '1';
	signal   nrst   : std_logic;
	signal   ov		: std_logic;
	signal   a		: std_logic_vector(nbits-1 downto 0);
	signal   b		: std_logic_vector(nbits-1 downto 0);
	signal   sum	: std_logic_vector(nbits-1 downto 0);

	-- test input vectors
	constant ntests : integer := 5;
	type vector_list is array(0 to ntests-1) of std_logic_vector(nbits-1 downto 0);
	signal operandA : vector_list := (x"01", x"68", x"AA", x"FE", x"FF");
	signal operandB : vector_list := (x"02", x"47", x"11", x"25", x"FF");

begin

	uut : entity work.sa(behavioral)
		  generic map(nbits => nbits)
		  port map(Clk  => clk,
				   nRst => nrst,
				   A	=> a,
				   B	=> b,
				   Sum  => sum,
			       Ov   => ov);

	-- generate clock signal
	clk <= not clk after period/2;

	-- apply stimulus to test device (try out a vareity of 
	process is
		variable i : integer := 0;
	begin

		nrst <= '0'; wait for 1.3*period;
		nrst <= '1';
		a	 <= operandA(i);
		b	 <= operandB(i);
		wait for nbits*period;

		wait until rising_edge(clk);
		
		if i = ntests-1 then
			wait;
		else
			i := i + 1;
		end if;

	end process;

end sim;

set3/q5/sa.vcd
$date
  Fri Nov 18 19:17:10 2022
$end
$version
  GHDL v0
$end
$timescale
  1 fs
$end
$scope module standard $end
$upscope $end
$scope module std_logic_1164 $end
$upscope $end
$scope module numeric_std $end
$upscope $end
$scope module sa_tb $end
$var reg 1 ! clk $end
$var reg 1 " nrst $end
$var reg 1 # ov $end
$var reg 8 $ a[7:0] $end
$var reg 8 % b[7:0] $end
$var reg 8 & sum[7:0] $end
$comment operanda is not handled $end
$comment operandb is not handled $end
$scope module uut $end
$var reg 1 ' clk $end
$var reg 1 ( nrst $end
$var reg 8 ) a[7:0] $end
$var reg 8 * b[7:0] $end
$var reg 8 + sum[7:0] $end
$var reg 1 , ov $end
$var reg 1 - carry $end
$upscope $end
$upscope $end
$enddefinitions $end
#0
1!
0"
0#
bUUUUUUUU $
bUUUUUUUU %
b00000000 &
1'
0(
bUUUUUUUU )
bUUUUUUUU *
b00000000 +
0,
0-
#5000000
0!
0'
#10000000
1!
1'
#13000000
1"
b00000001 $
b00000010 %
1(
b00000001 )
b00000010 *
#15000000
0!
0'
#20000000
1!
b00000001 &
1'
b00000001 +
#25000000
0!
0'
#30000000
1!
b00000011 &
1'
b00000011 +
#35000000
0!
0'
#40000000
1!
1'
#45000000
0!
0'
#50000000
1!
1'
#55000000
0!
0'
#60000000
1!
1'
#65000000
0!
0'
#70000000
1!
1'
#75000000
0!
0'
#80000000
1!
1'
#85000000
0!
0'
#90000000
1!
1'
#93000000
#95000000
0!
0'
#100000000
1!
0"
b00000000 &
1'
0(
b00000000 +
#105000000
0!
0'
#110000000
1!
1'
#113000000
1"
b01101000 $
b01000111 %
1(
b01101000 )
b01000111 *
#115000000
0!
0'
#120000000
1!
b00000001 &
1'
b00000001 +
#125000000
0!
0'
#130000000
1!
b00000011 &
1'
b00000011 +
#135000000
0!
0'
#140000000
1!
b00000111 &
1'
b00000111 +
#145000000
0!
0'
#150000000
1!
b00001111 &
1'
b00001111 +
#155000000
0!
0'
#160000000
1!
1'
#165000000
0!
0'
#170000000
1!
b00101111 &
1'
b00101111 +
#175000000
0!
0'
#180000000
1!
1#
1'
1,
1-
#185000000
0!
0'
#190000000
1!
0#
b10101111 &
1'
b10101111 +
0,
0-
#193000000
#195000000
0!
0'
#200000000
1!
0"
b00000000 &
1'
0(
b00000000 +
#205000000
0!
0'
#210000000
1!
1'
#213000000
1"
b10101010 $
b00010001 %
1(
b10101010 )
b00010001 *
#215000000
0!
0'
#220000000
1!
b00000001 &
1'
b00000001 +
#225000000
0!
0'
#230000000
1!
b00000011 &
1'
b00000011 +
#235000000
0!
0'
#240000000
1!
1'
#245000000
0!
0'
#250000000
1!
b00001011 &
1'
b00001011 +
#255000000
0!
0'
#260000000
1!
b00011011 &
1'
b00011011 +
#265000000
0!
0'
#270000000
1!
b00111011 &
1'
b00111011 +
#275000000
0!
0'
#280000000
1!
1'
#285000000
0!
0'
#290000000
1!
b10111011 &
1'
b10111011 +
#293000000
#295000000
0!
0'
#300000000
1!
0"
b00000000 &
1'
0(
b00000000 +
#305000000
0!
0'
#310000000
1!
1'
#313000000
1"
b11111110 $
b00100101 %
1(
b11111110 )
b00100101 *
#315000000
0!
0'
#320000000
1!
b00000001 &
1'
b00000001 +
#325000000
0!
0'
#330000000
1!
b00000011 &
1'
b00000011 +
#335000000
0!
0'
#340000000
1!
1#
1'
1,
1-
#345000000
0!
0'
#350000000
1!
1'
#355000000
0!
0'
#360000000
1!
1'
#365000000
0!
0'
#370000000
1!
b00100011 &
1'
b00100011 +
#375000000
0!
0'
#380000000
1!
1'
#385000000
0!
0'
#390000000
1!
1'
#393000000
#395000000
0!
0'
#400000000
1!
0"
0#
b00000000 &
1'
0(
b00000000 +
0,
0-
#405000000
0!
0'
#410000000
1!
1'
#413000000
1"
b11111111 $
b11111111 %
1(
b11111111 )
b11111111 *
#415000000
0!
0'
#420000000
1!
1#
1'
1,
1-
#425000000
0!
0'
#430000000
1!
b00000010 &
1'
b00000010 +
#435000000
0!
0'
#440000000
1!
b00000110 &
1'
b00000110 +
#445000000
0!
0'
#450000000
1!
b00001110 &
1'
b00001110 +
#455000000
0!
0'
#460000000
1!
b00011110 &
1'
b00011110 +
#465000000
0!
0'
#470000000
1!
b00111110 &
1'
b00111110 +
#475000000
0!
0'
#480000000
1!
b01111110 &
1'
b01111110 +
#485000000
0!
0'
#490000000
1!
b11111110 &
1'
b11111110 +
