set2/q1/successive3.vhd
-- successive3.vhd: Module to identify when the input sequence has the same value 
-- for 3 successive clock cycles

library ieee;
use ieee.std_logic_1164.all;

entity successive3 is
	port (
			-- input
		    clk : in std_logic;
			rst : in std_logic;
			s	: in std_logic;
			
			-- output
			y	: out std_logic
		);
end successive3;

architecture moore1 of successive3 is

	-- declare abstract state type and signal of that type
	type abstract_type is (SR, S01, S11, S02, S12, S03, S13);
	signal state : abstract_type;

begin

	-- sequential logic for driving state change at clock edge (or respond to reset)
	seq: process(clk, rst) is
	begin
		if rst = '1' then
			state <= SR;
		
		elsif rising_edge(clk) then
			case state is

				when SR =>
					if s = '1' then
						state <= S11;
					elsif s = '0' then
						state <= S01;
					end if;

				when S11 =>
					if s = '1' then
						state <= S12;
					elsif s = '0' then
						state <= S01;
					end if;

				when S12 =>
					if s = '1' then
						state <= S13;
					elsif s = '0' then
						state <= S01;
					end if;

				when S13 =>
					if s = '1' then
						state <= S11;
					elsif s = '0' then
						state <= S01;
					end if;

				when S01 =>
					if s = '0' then
						state <= S02;
					elsif s = '1' then
						state <= S11;
					end if;

				when S02 =>
					if s = '0' then
						state <= S03;
					elsif s = '1' then
						state <= S11;
					end if;

				when S03 =>
					if s = '0' then
						state <= S01;
					elsif s = '1' then
						state <= S11;
					end if;

			end case;
		end if;
	end process;

	-- combinational logic to produce output based on state (Moore Machine)
	y <= '1' when state = S13 or state = S03 else
		 '0';

end moore1;

set2/q1/successive3_tb.vhd
-- successive3_tb.vhd: Testbench to test the module for detecting a sequence of 3 
-- successive identical inputs

library ieee;
use ieee.std_logic_1164.all;
use ieee.numeric_std.all;

entity successive3_tb is
end successive3_tb;

architecture sim of successive3_tb is

	-- define clock parameters
	constant freq  : integer := 100e6;				-- 100 Mhz clock frequency
	constant cycle : time	 := 1000 ms / freq;		-- 1 clock cycle = 10 ns

	-- declare stimulus and response signals
	signal clk	   : std_logic := '1';
	signal rst 	   : std_logic := '0';
	signal s   	   : std_logic;
	signal y   	   : std_logic;
	signal stream  : std_logic_vector(19 downto 0):= "00011111101011000101";

begin 

	-- instantiate module
	uut : entity work.successive3(moore1) 
		  port map(clk => clk, rst => rst, s => s, y => y);

	-- generate clock signal
	clk <= not clk after cycle/2;

	-- apply stimulus to test uut
	process is 
	begin 

		-- initially hold reset for more than 1 cycle to offset input
		rst <= '1';
		wait for 1.3 * cycle;

		-- then bring uut device out of reset and apply bit stream
		rst <= '0';
		for i in (stream'length-1) downto 0 loop
			s <= '0';
			wait for 0.4*cycle;
			s <= stream(i);
			wait for 0.6*cycle;
		end loop;

		wait;
	end process;

end sim;

set2/q1/successive3.vcd
$date
  Fri Oct 28 02:32:18 2022
$end
$version
  GHDL v0
$end
$timescale
  1 fs
$end
$scope module standard $end
$upscope $end
$scope module std_logic_1164 $end
$upscope $end
$scope module numeric_std $end
$upscope $end
$scope module successive3_tb $end
$var reg 1 ! clk $end
$var reg 1 " rst $end
$var reg 1 # s $end
$var reg 1 $ y $end
$var reg 20 % stream[19:0] $end
$scope module uut $end
$var reg 1 & clk $end
$var reg 1 ' rst $end
$var reg 1 ( s $end
$var reg 1 ) y $end
$comment state is not handled $end
$upscope $end
$upscope $end
$enddefinitions $end
#0
1!
1"
U#
0$
b00011111101011000101 %
1&
1'
U(
0)
#5000000
0!
0&
#10000000
1!
1&
#13000000
0"
0#
0'
0(
#15000000
0!
0&
#17000000
#20000000
1!
1&
#23000000
#25000000
0!
0&
#27000000
#30000000
1!
1&
#33000000
#35000000
0!
0&
#37000000
#40000000
1!
1$
1&
1)
#43000000
#45000000
0!
0&
#47000000
1#
1(
#50000000
1!
0$
1&
0)
#53000000
0#
0(
#55000000
0!
0&
#57000000
1#
1(
#60000000
1!
1&
#63000000
0#
0(
#65000000
0!
0&
#67000000
1#
1(
#70000000
1!
1$
1&
1)
#73000000
0#
0(
#75000000
0!
0&
#77000000
1#
1(
#80000000
1!
0$
1&
0)
#83000000
0#
0(
#85000000
0!
0&
#87000000
1#
1(
#90000000
1!
1&
#93000000
0#
0(
#95000000
0!
0&
#97000000
1#
1(
#100000000
1!
1$
1&
1)
#103000000
0#
0(
#105000000
0!
0&
#107000000
#110000000
1!
0$
1&
0)
#113000000
#115000000
0!
0&
#117000000
1#
1(
#120000000
1!
1&
#123000000
0#
0(
#125000000
0!
0&
#127000000
#130000000
1!
1&
#133000000
#135000000
0!
0&
#137000000
1#
1(
#140000000
1!
1&
#143000000
0#
0(
#145000000
0!
0&
#147000000
1#
1(
#150000000
1!
1&
#153000000
0#
0(
#155000000
0!
0&
#157000000
#160000000
1!
1&
#163000000
#165000000
0!
0&
#167000000
#170000000
1!
1&
#173000000
#175000000
0!
0&
#177000000
#180000000
1!
1$
1&
1)
#183000000
#185000000
0!
0&
#187000000
1#
1(
#190000000
1!
0$
1&
0)
#193000000
0#
0(
#195000000
0!
0&
#197000000
#200000000
1!
1&
#203000000
#205000000
0!
0&
#207000000
1#
1(
#210000000
1!
1&
#213000000
#215000000
0!
0&
#220000000
1!
1&
#225000000
0!
0&
#230000000
1!
1$
1&
1)
#235000000
0!
0&
#240000000
1!
0$
1&
0)
#245000000
0!
0&
#250000000
1!
1&
#255000000
0!
0&
#260000000
1!
1$
1&
1)
#265000000
0!
0&
#270000000
1!
0$
1&
0)
#275000000
0!
0&
#280000000
1!
1&
#285000000
0!
0&
#290000000
1!
1$
1&
1)
#295000000
0!
0&
#300000000
1!
0$
1&
0)
